nexus_analyzer-2026.1.2.dist-info/licenses/LICENSE
nexus_cli/__init__.py
nexus_cli/cli.py
nexus_cli/nexus_analyzer.py
nexus_analyzer-2026.1.2.dist-info/METADATA
nexus_analyzer-2026.1.2.dist-info/WHEEL
nexus_analyzer-2026.1.2.dist-info/entry_points.txt
nexus_analyzer-2026.1.2.dist-info/top_level.txt
nexus_analyzer-2026.1.2.dist-info/RECORD
