Metadata-Version: 2.4
Name: nexus-analyzer
Version: 2026.1.2
Summary: Comprehensive Python project analysis and reporting tool
Author-email: Muslu Yüksektepe <musluyuksektepe@gmail.com>, Ali Alın <alialinxz@gmail.com>, Doğancan Avcı <dogancannavci@gmail.com>
License-Expression: MIT
Keywords: python,cli,analysis,dependency,infrastructure
Requires-Python: >=3.9
License-File: LICENSE
Dynamic: license-file
